synergy_scheduler_manager/__init__.py
synergy_scheduler_manager/fairshare_manager.py
synergy_scheduler_manager/keystone_manager.py
synergy_scheduler_manager/nova_manager.py
synergy_scheduler_manager/project_manager.py
synergy_scheduler_manager/queue_manager.py
synergy_scheduler_manager/quota_manager.py
synergy_scheduler_manager/scheduler_manager.py
synergy_scheduler_manager/auth/__init__.py
synergy_scheduler_manager/auth/plugin.py
synergy_scheduler_manager/client/__init__.py
synergy_scheduler_manager/client/command.py
synergy_scheduler_manager/common/__init__.py
synergy_scheduler_manager/common/block_device.py
synergy_scheduler_manager/common/compute.py
synergy_scheduler_manager/common/domain.py
synergy_scheduler_manager/common/endpoint.py
synergy_scheduler_manager/common/flavor.py
synergy_scheduler_manager/common/hypervisor.py
synergy_scheduler_manager/common/messaging.py
synergy_scheduler_manager/common/priority.py
synergy_scheduler_manager/common/project.py
synergy_scheduler_manager/common/queue.py
synergy_scheduler_manager/common/quota.py
synergy_scheduler_manager/common/request.py
synergy_scheduler_manager/common/role.py
synergy_scheduler_manager/common/server.py
synergy_scheduler_manager/common/service.py
synergy_scheduler_manager/common/share.py
synergy_scheduler_manager/common/token.py
synergy_scheduler_manager/common/trust.py
synergy_scheduler_manager/common/user.py
synergy_scheduler_manager/common/utils.py
synergy_scheduler_manager/tests/__init__.py
synergy_scheduler_manager/tests/functional/__init__.py
synergy_scheduler_manager/tests/functional/test_fairshare_manager.py
synergy_scheduler_manager/tests/functional/test_scheduler_manager.py
synergy_scheduler_manager/tests/unit/__init__.py
synergy_scheduler_manager/tests/unit/base.py
synergy_scheduler_manager/tests/unit/test_block_device.py
synergy_scheduler_manager/tests/unit/test_compute.py
synergy_scheduler_manager/tests/unit/test_endpoint.py
synergy_scheduler_manager-2.6.0.dist-info/DESCRIPTION.rst
synergy_scheduler_manager-2.6.0.dist-info/METADATA
synergy_scheduler_manager-2.6.0.dist-info/RECORD
synergy_scheduler_manager-2.6.0.dist-info/WHEEL
synergy_scheduler_manager-2.6.0.dist-info/entry_points.txt
synergy_scheduler_manager-2.6.0.dist-info/metadata.json
synergy_scheduler_manager-2.6.0.dist-info/pbr.json
synergy_scheduler_manager-2.6.0.dist-info/top_level.txt
