Metadata-Version: 2.0
Name: synergy-scheduler-manager
Version: 2.6.0
Summary: Provide advanced scheduling (fairshare) capability for OpenStack
Home-page: https://launchpad.net/synergy-scheduler-manager
Author: Lisa Zangrando
Author-email: lisa.zangrando@pd.infn.it
License: UNKNOWN
Platform: UNKNOWN
Classifier: Environment :: OpenStack
Classifier: Intended Audience :: Information Technology
Classifier: Intended Audience :: System Administrators
Classifier: License :: OSI Approved :: Apache Software License
Classifier: Operating System :: POSIX :: Linux
Classifier: Programming Language :: Python
Classifier: Programming Language :: Python :: 2
Classifier: Programming Language :: Python :: 2.7
Requires-Dist: pbr
Requires-Dist: oslo.config
Requires-Dist: oslo.messaging
Requires-Dist: oslo.serialization
Requires-Dist: oslo.versionedobjects
Requires-Dist: requests
Requires-Dist: sqlalchemy
Requires-Dist: synergy-service (<1.7,>=1.5)
